csv_logger/__init__.py
csv_logger/adapter.py
csv_logger/handler.py
pycsvlogger-0.1.2.dist-info/licenses/LICENSE
pycsvlogger-0.1.2.dist-info/METADATA
pycsvlogger-0.1.2.dist-info/WHEEL
pycsvlogger-0.1.2.dist-info/top_level.txt
pycsvlogger-0.1.2.dist-info/RECORD
