Metadata-Version: 2.4
Name: pycsvlogger
Version: 0.1.2
Summary: Flexible, general-purpose CSV-based structured logging for Python
Home-page: https://github.com/MahiSBora/pycsvlogger.git
Author: Mahipal Bora
Author-email: mahi123bora@gmail.com
License: MIT
Classifier: Programming Language :: Python :: 3
Classifier: License :: OSI Approved :: MIT License
Classifier: Operating System :: OS Independent
Requires-Python: >=3.7
License-File: LICENSE
Dynamic: author
Dynamic: author-email
Dynamic: classifier
Dynamic: description
Dynamic: description-content-type
Dynamic: home-page
Dynamic: license
Dynamic: license-file
Dynamic: requires-python
Dynamic: summary
